hape/__init__.py
hape/bootstrap.py
hape/cli.py
hape/config.py
hape/hape_config.py
hape/logging.py
hape/playground.py
hape/argument_parsers/__init__.py
hape/argument_parsers/config_argument_parser.py
hape/argument_parsers/git_argument_parser.py
hape/argument_parsers/k8s_deployment_argument_parser.py
hape/argument_parsers/k8s_deployment_cost_argument_parser.py
hape/argument_parsers/main_argument_parser.py
hape/argument_parsers/playground_argument_parser.py
hape/base/__init__.py
hape/base/model.py
hape/base/model_argument_parser.py
hape/base/model_controller.py
hape/controllers/__init__.py
hape/controllers/git_controller.py
hape/controllers/k8s_deployment_controller.py
hape/controllers/k8s_deployment_cost_controller.py
hape/enums/__init__.py
hape/enums/environment_variables_enum.py
hape/enums/kube_context_enum.py
hape/enums/log_level_enum.py
hape/hape_cli/__init__.py
hape/hape_cli/cli.py
hape/hape_cli/argument_parsers/__init__.py
hape/hape_cli/argument_parsers/crud_argument_parser.py
hape/hape_cli/argument_parsers/init_argument_parser.py
hape/hape_cli/argument_parsers/json_argument_parser.py
hape/hape_cli/argument_parsers/main_argument_parser.py
hape/hape_cli/argument_parsers/yaml_argument_parser.py
hape/hape_cli/controllers/__init__.py
hape/hape_cli/controllers/crud_controller.py
hape/hape_cli/controllers/init_controller.py
hape/hape_cli/controllers/json_controller.py
hape/hape_cli/controllers/yaml_controller.py
hape/hape_cli/crud_templates/argument_parser_template.py
hape/hape_cli/crud_templates/controller_template.py
hape/hape_cli/crud_templates/migration_template.py
hape/hape_cli/crud_templates/model_template.py
hape/hape_cli/enums/__init__.py
hape/hape_cli/enums/crud_actions.py
hape/hape_cli/enums/crud_column_fk_on_delete.py
hape/hape_cli/enums/crud_column_valid_properties.py
hape/hape_cli/enums/crud_column_valid_types.py
hape/hape_cli/init_templates/__init__.py
hape/hape_cli/init_templates/alembic_template.py
hape/hape_cli/init_templates/dockerfiles_templates.py
hape-0.2.119.dist-info/licenses/LICENSE.md
hape-0.2.119.dist-info/METADATA
hape-0.2.119.dist-info/WHEEL
hape-0.2.119.dist-info/entry_points.txt
hape-0.2.119.dist-info/top_level.txt
hape-0.2.119.dist-info/RECORD
