Metadata-Version: 2.4
Name: hape
Version: 0.2.119
Summary: HAPE Framework: Build an Automation Tool With Ease
Home-page: https://github.com/hazemataya94/hape-framework
Author: Hazem Ataya
Author-email: hazem.ataya94@gmail.com
Classifier: Programming Language :: Python :: 3
Classifier: License :: OSI Approved :: MIT License
Classifier: Operating System :: OS Independent
Requires-Python: >=3.9
License-File: LICENSE.md
Requires-Dist: alembic==1.14.1
Requires-Dist: build==1.2.2.post1
Requires-Dist: cachetools==5.5.1
Requires-Dist: certifi==2024.12.14
Requires-Dist: cffi==1.17.1
Requires-Dist: charset-normalizer==3.4.1
Requires-Dist: cryptography==44.0.0
Requires-Dist: docutils==0.21.2
Requires-Dist: durationpy==0.9
Requires-Dist: google-auth==2.38.0
Requires-Dist: greenlet==3.1.1
Requires-Dist: idna==3.10
Requires-Dist: iniconfig==2.0.0
Requires-Dist: jaraco.classes==3.4.0
Requires-Dist: jaraco.context==6.0.1
Requires-Dist: jaraco.functools==4.1.0
Requires-Dist: keyring==25.6.0
Requires-Dist: kubernetes==31.0.0
Requires-Dist: Mako==1.3.8
Requires-Dist: markdown-it-py==3.0.0
Requires-Dist: MarkupSafe==3.0.2
Requires-Dist: mdurl==0.1.2
Requires-Dist: more-itertools==10.6.0
Requires-Dist: mysql==0.0.3
Requires-Dist: mysql-connector-python==9.2.0
Requires-Dist: mysqlclient==2.2.7
Requires-Dist: nh3==0.2.20
Requires-Dist: oauthlib==3.2.2
Requires-Dist: packaging==24.2
Requires-Dist: pkginfo==1.12.0
Requires-Dist: pluggy==1.5.0
Requires-Dist: pyasn1==0.6.1
Requires-Dist: pyasn1_modules==0.4.1
Requires-Dist: pycparser==2.22
Requires-Dist: Pygments==2.19.1
Requires-Dist: PyMySQL==1.1.1
Requires-Dist: pyproject_hooks==1.2.0
Requires-Dist: pytest==8.3.4
Requires-Dist: python-dateutil==2.9.0.post0
Requires-Dist: python-dotenv==1.0.1
Requires-Dist: python-gitlab==5.6.0
Requires-Dist: python-json-logger==3.2.1
Requires-Dist: PyYAML==6.0.2
Requires-Dist: readme_renderer==44.0
Requires-Dist: requests==2.32.3
Requires-Dist: requests-oauthlib==2.0.0
Requires-Dist: requests-toolbelt==1.0.0
Requires-Dist: rfc3986==2.0.0
Requires-Dist: rich==13.9.4
Requires-Dist: rsa==4.9
Requires-Dist: ruamel.yaml==0.18.10
Requires-Dist: ruamel.yaml.clib==0.2.12
Requires-Dist: setuptools==75.8.0
Requires-Dist: six==1.17.0
Requires-Dist: SQLAlchemy==2.0.37
Requires-Dist: twine==6.0.1
Requires-Dist: typing_extensions==4.12.2
Requires-Dist: urllib3==2.3.0
Requires-Dist: websocket-client==1.8.0
Requires-Dist: wheel==0.45.1
Dynamic: author
Dynamic: author-email
Dynamic: classifier
Dynamic: description
Dynamic: description-content-type
Dynamic: home-page
Dynamic: license-file
Dynamic: requires-dist
Dynamic: requires-python
Dynamic: summary
